odoo/addons/dms_res_model_root_directory/CHANGELOG.md
odoo/addons/dms_res_model_root_directory/README.rst
odoo/addons/dms_res_model_root_directory/__init__.py
odoo/addons/dms_res_model_root_directory/__manifest__.py
odoo/addons/dms_res_model_root_directory/demo/dms_category.xml
odoo/addons/dms_res_model_root_directory/demo/dms_directory.xml
odoo/addons/dms_res_model_root_directory/i18n/ca_ES.po
odoo/addons/dms_res_model_root_directory/i18n/es.po
odoo/addons/dms_res_model_root_directory/models/__init__.py
odoo/addons/dms_res_model_root_directory/models/dms_directory.py
odoo/addons/dms_res_model_root_directory/models/dms_file.py
odoo/addons/dms_res_model_root_directory/models/ir_attachment.py
odoo/addons/dms_res_model_root_directory/services/__init__.py
odoo/addons/dms_res_model_root_directory/services/record_directory_service.py
odoo/addons/dms_res_model_root_directory/static/description/icon.png
odoo/addons/dms_res_model_root_directory/static/description/ticket.png
odoo/addons/dms_res_model_root_directory/tests/__init__.py
odoo/addons/dms_res_model_root_directory/tests/models/__init__.py
odoo/addons/dms_res_model_root_directory/tests/models/test_dms_directory.py
odoo/addons/dms_res_model_root_directory/tests/models/test_dms_file.py
odoo/addons/dms_res_model_root_directory/tests/models/test_ir_attachment.py
odoo/addons/dms_res_model_root_directory/tests/services/__init__.py
odoo/addons/dms_res_model_root_directory/tests/services/test_record_directory_service.py
odoo/addons/dms_res_model_root_directory/tests/wizards/__init__.py
odoo/addons/dms_res_model_root_directory/tests/wizards/test_add_dms_file_wizard.py
odoo/addons/dms_res_model_root_directory/views/res_partner_views.xml
odoo/addons/dms_res_model_root_directory/wizards/__init__.py
odoo/addons/dms_res_model_root_directory/wizards/add_dms_file/__init__.py
odoo/addons/dms_res_model_root_directory/wizards/add_dms_file/add_dms_file.py
odoo/addons/dms_res_model_root_directory/wizards/add_dms_file/add_dms_file.xml
odoo12_addon_dms_res_model_root_directory-12.0.0.1.0.99.dev1.dist-info/METADATA
odoo12_addon_dms_res_model_root_directory-12.0.0.1.0.99.dev1.dist-info/WHEEL
odoo12_addon_dms_res_model_root_directory-12.0.0.1.0.99.dev1.dist-info/top_level.txt
odoo12_addon_dms_res_model_root_directory-12.0.0.1.0.99.dev1.dist-info/RECORD
