Metadata-Version: 2.1
Name: odoo12-addon-dms-res-model-root-directory
Version: 12.0.0.1.0.99.dev1
Summary: Implement a new dms directory structure based on unique root directory by model and category. Each file can be created in a model instance particular directory under a root directory.
Home-page: https://gitlab.com/somitcoop/erp-research/odoo-helpdesk
Author: Som It Cooperatiu SCCL, Som Connexió SCCL,
License: AGPL-3
Platform: UNKNOWN
Classifier: Programming Language :: Python
Classifier: Framework :: Odoo
Classifier: Framework :: Odoo :: 12.0
Classifier: License :: OSI Approved :: GNU Affero General Public License v3
Requires-Python: >=3.5
Requires-Dist: odoo12-addon-component-event
Requires-Dist: odoo12-addon-dms
Requires-Dist: odoo <12.1dev,>=12.0a
